selector/__init__.py
selector/best_conf.py
selector/cleanup.py
selector/configuration_translator.py
selector/hp_point_selection.py
selector/instance_monitor.py
selector/instance_sets.py
selector/log_setup.py
selector/main.py
selector/mini_tournaments.py
selector/point_gen.py
selector/pointselector.py
selector/pool.py
selector/read_files.py
selector/run_ac.py
selector/scenario.py
selector/selection_features.py
selector/ta_execution.py
selector/ta_result_store.py
selector/test_ray.py
selector/tournament_bookkeeping.py
selector/tournament_dispatcher.py
selector/tournament_monitor.py
selector/tournament_performance.py
selector/winner_instance_monitor.py
selector/generators/__init__.py
selector/generators/default_point_generator.py
selector/generators/lhs_point_generator.py
selector/generators/random_point_generator.py
selector/generators/variable_graph_point_generator.py
selector/generators/surrogates/__init__.py
selector/generators/surrogates/cppl_surrogate.py
selector/generators/surrogates/ggapp_surrogate.py
selector/generators/surrogates/smac_surrogate.py
selector/generators/surrogates/surrogates.py
selector_ac-0.1.0.4.dist-info/LICENSE
selector_ac-0.1.0.4.dist-info/METADATA
selector_ac-0.1.0.4.dist-info/WHEEL
selector_ac-0.1.0.4.dist-info/top_level.txt
selector_ac-0.1.0.4.dist-info/RECORD
