Metadata-Version: 2.1
Name: selector-ac
Version: 0.1.0.4
Summary: Selector: Ensemble-Based Automated Algorithm Configuration
Home-page: https://github.com/DOTBielefeld/selector
Author: DOT
Author-email: dimitri-weiss@web.de
License: MIT License
Classifier: Natural Language :: English
Classifier: Intended Audience :: Developers
Classifier: Intended Audience :: Education
Classifier: Intended Audience :: Science/Research
Classifier: Operating System :: POSIX :: Linux
Classifier: License :: OSI Approved :: MIT License
Classifier: Programming Language :: Python :: 3
Classifier: Programming Language :: Python :: 3.8
Requires-Python: >=3.8
License-File: LICENSE
Requires-Dist: swig==4.1.1
Requires-Dist: aiohttp==3.8.1
Requires-Dist: aiohttp-cors==0.7.0
Requires-Dist: aioredis==1.3.1
Requires-Dist: aiosignal==1.2.0
Requires-Dist: async-timeout==4.0.2
Requires-Dist: asynctest==0.13.0
Requires-Dist: attrs==21.4.0
Requires-Dist: blessed==1.19.0
Requires-Dist: cachetools==4.2.4
Requires-Dist: certifi==2021.10.8
Requires-Dist: charset-normalizer==2.0.10
Requires-Dist: click==8.0.3
Requires-Dist: colorful==0.5.4
Requires-Dist: ConfigSpace==0.5.0
Requires-Dist: costcla==0.6
Requires-Dist: Deprecated==1.2.13
Requires-Dist: filelock==3.4.2
Requires-Dist: frozenlist==1.2.0
Requires-Dist: google-api-core==2.4.0
Requires-Dist: google-auth==2.3.3
Requires-Dist: googleapis-common-protos==1.54.0
Requires-Dist: gpustat==1.0.0b1
Requires-Dist: grpcio==1.43.0
Requires-Dist: hiredis==2.0.0
Requires-Dist: idna==3.3
Requires-Dist: importlib-metadata==4.10.0
Requires-Dist: importlib-resources==5.4.0
Requires-Dist: jsonschema==4.4.0
Requires-Dist: joblib==1.1.0
Requires-Dist: msgpack==1.0.3
Requires-Dist: multidict==5.2.0
Requires-Dist: numpy==1.21.5
Requires-Dist: nvidia-ml-py3==7.352.0
Requires-Dist: opencensus==0.8.0
Requires-Dist: opencensus-context==0.1.2
Requires-Dist: packaging==22.0
Requires-Dist: prometheus-client==0.12.0
Requires-Dist: protobuf==3.19.3
Requires-Dist: psutil==5.9.0
Requires-Dist: pyrfr==0.8.0
Requires-Dist: py-spy==0.3.11
Requires-Dist: pyasn1==0.4.8
Requires-Dist: pyasn1-modules==0.2.8
Requires-Dist: pyparsing==3.0.6
Requires-Dist: pyrsistent==0.18.0
Requires-Dist: PyYAML==6.0
Requires-Dist: ray==2.3.1
Requires-Dist: redis==4.1.0
Requires-Dist: requests==2.27.1
Requires-Dist: rsa==4.8
Requires-Dist: six==1.16.0
Requires-Dist: scikit-learn==1.0.2
Requires-Dist: scikit-learn-extra==0.3.0
Requires-Dist: scikit-optimize==0.9.0
Requires-Dist: smac==1.3.3
Requires-Dist: smart-open==5.2.1
Requires-Dist: typing-extensions==4.0.1
Requires-Dist: urllib3==1.26.8
Requires-Dist: wcwidth==0.2.5
Requires-Dist: wrapt==1.13.3
Requires-Dist: yarl==1.7.2
Requires-Dist: zipp==3.7.0
